Workbook

Sheet Module_Planification
A1: PRS 2.0 — Module 1 : socle transversal et dossiers de planification (Gantt hebdomadaire)
A2: Arrêté au 01/09/2026 · 27 lignes · démarrage 17/06/2026 · échéance 18/09/2026
A3: ID | B3: Activité | C3: Livrable | D3: Responsable | E3: Statut | F3: % | G3: Début | H3: Fin | I3: Durée (j) | J3: Dépend. | K3: Jalon | L3: Critique | M3: Preuve / constat | N3: S1 | O3: S2 | P3: S3 | Q3: S4 | R3: S5 | S3: S6 | T3: S7 | U3: S8 | V3: S9 | W3: S10 | X3: S11 | Y3: S12 | Z3: S13 | AA3: S14
A4: — | N4: =Parametres!$B$2+0 -> 46190 | O4: =Parametres!$B$2+7 -> 46197 | P4: =Parametres!$B$2+14 -> 46204 | Q4: =Parametres!$B$2+21 -> 46211 | R4: =Parametres!$B$2+28 -> 46218 | S4: =Parametres!$B$2+35 -> 46225 | T4: =Parametres!$B$2+42 -> 46232 | U4: =Parametres!$B$2+49 -> 46239 | V4: =Parametres!$B$2+56 -> 46246 | W4: =Parametres!$B$2+63 -> 46253 | X4: =Parametres!$B$2+70 -> 46260 | Y4: =Parametres!$B$2+77 -> 46267 | Z4: =Parametres!$B$2+84 -> 46274 | AA4: =Parametres!$B$2+91 -> 46281
A5: A01 | B5: Socle d'authentification et d'habilitations | C5: Connexion, contrôle d'accès par profil et par entité, socle commun d'appel à l'API | D5: Mr Lanto | E5: termine | F5: 1 | G5: =Parametres!$B$2+0 -> 46190 | H5: =Parametres!$B$2+2 -> 46192 | I5: 3 | L5: ◆ oui | M5: commit 62f5f9a (17/06) — création de core/auth/{auth.service,auth.guard,permissions.service,permissions}.ts et services/api/crud.service.ts ; couvert par auth.service.spec.ts, auth.guard.spec.ts, permissions.service.spec.ts (suite complète 85/85 au vert, `ng test` du 26/08)
A6: A02 | B6: Circuit d'instruction d'un dossier, du dépôt au procès-verbal | C6: Enchaînement dépôt → réception → affectation → examen → procès-verbal, et les écrans des six profils qui l'exercent | D6: Mr Mathieu | E6: termine | F6: 1 | G6: =Parametres!$B$2+0 -> 46190 | H6: =Parametres!$B$2+8 -> 46198 | I6: 7 | J6: A01 | L6: ◆ oui | M6: commit 62f5f9a (17/06) — shared/circuit/{circuit-workflow,pv-workflow,circuit-timeline,statut-badge}.ts + circuit-workflow.spec.ts ; features/circuit/{dispatch-form,dossier-consultation,dossiers-pipeline}.ts ; features/membre/{examen-dossier,pv-page}.ts ; features/secretaire/{receptions,enregistrement}.ts ; complété par les 4 commits du 18/06 (worklists de vérification)
A7: A03 | B7: Retrait d'un dossier et décision du contrôleur | C7: Écran de demande pour l'autorité contractante, écran de décision pour le Président et le Chef de commission, retrait bloqué dès la signature du procès-verbal | D7: Mr Mathieu | E7: termine | F7: 1 | G7: =Parametres!$B$2+1 -> 46191 | H7: =Parametres!$B$2+6 -> 46196 | I7: 4 | J7: A02 | M7: features/circuit/retraits-validation.ts créé le 18/06 ; features/cc/retraits-decision.ts et features/prmp/retraits.ts au commit initial ; règle « retrait impossible dès PV_SIGNE » (409) — commits du 23/06 « message liste vide explicite + erreur 409 dédiée »
A8: A04 | B8: Rectification par l'autorité contractante et navette de vérification | C8: Renvoi d'un dossier pour rectification, fil des échanges entre le vérificateur et l'autorité contractante, reprise de l'instruction après correction | D8: Mr Mathieu | E8: termine | F8: 1 | G8: =Parametres!$B$2+2 -> 46192 | H8: =Parametres!$B$2+6 -> 46196 | I8: 3 | J8: A02 | M8: 12 commits du 19/06 (« statut EN_ATTENTE_DECISION_PRMP (obs non levées) bout-en-bout », « resoumission après rectification ») ; création de features/prmp/dossiers-a-rectifier.ts et features/verificateur/en-attente-prmp.ts le 19/06
A9: A05 | B9: Lettre de renvoi et intervention de l'assistant contrôleur | C9: Seconde issue de l'examen à côté du procès-verbal : rédaction, mise à la signature et consultation de la lettre de renvoi | D9: Mr Mathieu | E9: termine | F9: 1 | G9: =Parametres!$B$2+7 -> 46197 | H9: =Parametres!$B$2+8 -> 46198 | I9: 2 | J9: A02 | K9: J1 | M9: features/membre/lettre-renvois.ts créé le 24/06 ; features/circuit/{pv-assistant,lettre-renvoi-consultation}.ts et features/assistant/assistant.routes.ts créés le 25/06 ; 8 commits du 25/06 | O9: ◆
A10: A06 | B10: Charte graphique et harmonisation de tous les écrans | C10: Jeu commun de composants, de couleurs et de typographies, appliqué aux écrans des neuf espaces de travail | D10: Mr Christian | E10: termine | F10: 1 | G10: =Parametres!$B$2+12 -> 46202 | H10: =Parametres!$B$2+13 -> 46203 | I10: 2 | J10: A02 | M10: 50 commits le 26/06/2026 — pic d'activité du dépôt — dont 18 intitulés « migrer … vers le design system » (layout, PRMP, circuit, CRUD, secrétaire, président, pilotage, admin, auth) ; création de src/styles/_design-system.scss
A11: A07 | B11: Compteurs de menu et tableaux de bord par profil | C11: Nombre de dossiers en attente affiché sur chaque entrée de menu, tableau de bord des indicateurs et écran de rapports | D11: Mr Christian | E11: termine | F11: 1 | G11: =Parametres!$B$2+12 -> 46202 | H11: =Parametres!$B$2+15 -> 46205 | I11: 4 | J11: A06 | M11: 13 commits du 29/06 (« compteurs du menu PRMP / Vérificateur / Secrétaire », « compteurs scopés par localité pour le CC ») ; features/pilotage/{kpi-dashboard,rapports-page}.ts et shared/dashboard/dashboard-shell.ts ; endpoint agrégé GET /api/kpis/badges livré au commit fad4ca7
A12: A08 | B12: Administration des référentiels | C12: Écrans de gestion des entités contractantes, des autorités de passation, des unités de gestion, des pièces exigées et des modes de passation | D12: Mr Christian | E12: termine | F12: 1 | G12: =Parametres!$B$2+16 -> 46206 | H12: =Parametres!$B$2+29 -> 46219 | I12: 10 | J12: A01 | M12: features/admin/admin-resources.config.ts (~600 lignes) et admin.routes.ts (21 `loadComponent`) ; ugpm-admin.ts créé le 06/07 ; controleur-admin.ts, prmp-admin.ts, inscriptions-admin.ts, prmp-pieces-admin.ts, ugpm-pieces-admin.ts, dmc-mapping-admin.ts créés le 16/07
A13: A09 | B13: Saisie du plan de passation et reprise automatique du document PDF | C13: Grille de saisie des lignes de marché, import d'un plan au format PDF avec revue ligne à ligne, calendrier prévisionnel par processus de passation | D13: Mr Christian | E13: termine | F13: 1 | G13: =Parametres!$B$2+6 -> 46196 | H13: =Parametres!$B$2+40 -> 46230 | I13: 24 | J13: A02 | L13: ◆ oui | M13: 20 commits du 23/06 (dates prévisionnelles par marché, référentiel CAPM, cohérence chronologique) ; shared/prmp/ppm-marches-table.ts créé le 05/07 ; ppm-form-factory.ts et ppm-saisie-grid.ts créés le 23/07 (« grille de saisie riche partagée », « soumettre consomme la grille partagée ») ; UI d'import .xlsx retirée volontairement le 22/07
A14: A10 | B14: Typologie des dossiers : familles et sous-types | C14: Choix de la famille au dépôt (planification, mise en concurrence, marché), sous-type déterminé par le serveur, grille de points de contrôle propre à chaque sous-type | D14: Mr Christian | E14: termine | F14: 1 | G14: =Parametres!$B$2+29 -> 46219 | H14: =Parametres!$B$2+40 -> 46230 | I14: 8 | J14: A08, A09 | L14: ◆ oui | M14: features/prmp/{dossiers-liste,mes-dossiers}.ts créés le 16/07 ; soumettre-dossier.ts:57-61 (`type FamilleDossier = 'DMC' | 'DDM'`) et :947-960 ; models/referentiel.model.ts:184-198 (tr_type_dossier, tr_sous_type_dossier) ; models/circuit.model.ts:13-15
A15: A11 | B15: Rattachement de l'entité contractante au dépôt d'un dossier | C15: Reconnaissance ou création de l'entité au moment de l'import, approbation par l'administrateur, localité du dossier déduite de l'entité | D15: Mr Christian | E15: termine | F15: 1 | G15: =Parametres!$B$2+40 -> 46230 | H15: =Parametres!$B$2+40 -> 46230 | I15: 1 | J15: A08, A09 | M15: 20 commits le 26/07/2026 (dimanche) : « création d'une entité contractante à l'import », « écran Rattachements en attente », « localité de l'entité → localité du dossier dérivée » ; features/admin/rattachements-admin.ts créé le 26/07
A16: A12 | B16: Files de travail « Mes dossiers » de chaque profil | C16: Écran unique par profil regroupant les dossiers à traiter, classés par étape ; vue de la charge par contrôleur pour le Président | D16: Mr Mathieu | E16: termine | F16: 1 | G16: =Parametres!$B$2+40 -> 46230 | H16: =Parametres!$B$2+40 -> 46230 | I16: 1 | J16: A10, A11 | K16: J2 | L16: ◆ oui | M16: features/circuit/{dossiers-classement,dossiers-circuit-liste}.ts créés le 26/07 ; features/president/dispatchs-controleurs.ts créé le 27/07 ; 20 commits du 27/07, dont « écrans redondants supprimés — files d'examen dans Mes dossiers » | S16: ◆
A17: A13 | B17: Interruption : chantier parallèle et attente du backend | C17: Aucun — période sans production sur ce dépôt | D17: Mr Lanto, Mr Mathieu, Mr Christian | E17: termine | F17: 1 | G17: =Parametres!$B$2+41 -> 46231 | H17: =Parametres!$B$2+54 -> 46244 | I17: 10 | J17: A12 | M17: 0 commit du 28/07/2026 au 10/08/2026 inclus (`git log --pretty=%ad --date=short | sort | uniq -c`) — période qualifiée par le pilote le 26/08 : chantier parallèle / attente
A18: A14 | B18: Délégation ascendante et mandats des autorités de passation | C18: Exercice des tâches d'un profil subordonné par son supérieur, journal des mandats et signalement des périodes de vacance | D18: Mr Mathieu | E18: termine | F18: 1 | G18: =Parametres!$B$2+55 -> 46245 | H18: =Parametres!$B$2+58 -> 46248 | I18: 4 | J18: A01, A12 | L18: ◆ oui | M18: features/admin/mandats-admin.ts et core/vacance/vacance.store.ts créés le 12/08 ; commit du 14/08 « délégation ascendante pilotée par les données (t_delegation_profil) » puis « écrans des subordonnés chez Président/CC (Lot 2) » ; ba9aa97 (15/08) interrupteurs « Délégations »
A19: A15 | B19: Notifications en temps réel | C19: Alerte immédiate à l'écran, compteur de messages non lus et écran de consultation ouvert aux dix profils | D19: Mr Lanto | E19: termine | F19: 1 | G19: =Parametres!$B$2+55 -> 46245 | H19: =Parametres!$B$2+58 -> 46248 | I19: 4 | J19: A01 | M19: core/notifications/notification-route.ts et features/transverse/notifications-page.ts créés le 11/08 (« clic → écran d'action, mapping type × rôle ») ; notifications.store.ts créé le 15/08 au commit 9552c0c
A20: A16 | B20: Observations du procès-verbal et navette après signature | C20: Suivi de chaque observation jusqu'à sa levée, décisions du vérificateur, réexamen d'un dossier rectifié, formulaire de réception commun aux profils | D20: Mr Mathieu | E20: termine | F20: 1 | G20: =Parametres!$B$2+55 -> 46245 | H20: =Parametres!$B$2+58 -> 46248 | I20: 4 | J20: A02, A09 | M20: commits du 15/08 : ce4e875 (cartes d'observation + passage vérificateur par décisions), 018ffae (table PPM commune, mise à jour par import, pièces au dépôt), f6db187 (navette post-signature : archivage, réexamen), 7dbb42d (formulaire de réception partagé) ; création de shared/circuit/observation-pv-card.ts, features/circuit/reception-form.ts, features/prmp/{completer-pieces-depot-modal,mise-a-jour-ppm}.ts
A21: A17 | B21: Traitement des constats de l'audit technique | C21: Correction des 35 constats de sécurité, d'accessibilité, de performance et de dépendances, chacun vérifié et tracé dans AUDIT.md | D21: Mr Lanto | E21: en_retard | F21: 0.86 | G21: =Parametres!$B$2+61 -> 46251 | H21: =Parametres!$B$2+63 -> 46253 | I21: 3 | J21: A06 | M21: AUDIT.md §3 dénombre 35 constats (S1-S13, P1-P11, A1-A7, T1-T3, D1), auxquels s'ajoute C-1 issu du nouvel audit global du 27/08 — soit 36. Clos et vérifiés : 31. Chantiers du 27/08 (AUDIT.md, deux entrées) : les 124 avertissements ESLint d'accessibilité soldés (6523668 → 1d097e5, 8 commits, 34 fichiers — le clic sur le voile passe dans la directive appModale) ; P1 ENFIN ADOPTÉ (238293b → b103221, 20 commits : recherche de la topbar résolue côté serveur, « Mes dossiers » et pipeline paginés, rendu incrémental des trois files sans endpoint paginé) ; P9 étendu ; C-1 clos le jour même. S9 CLOS le 31/08 (ffd84a8) : rendu sans objet par le retrait des interrupteurs de délégation (23d7e7f, 28/08) — la clé n'est plus écrite, purge au logout, cinq mentions annotées dans AUDIT.md. Restent ouverts : A2b, S12, P10, T1 (entamé), T3 = 5. Avancement = 31/36 = 86 % (était 30/36 = 83 % au 28/08).
A22: A18 | B22: Sécurisation de la session par cookie | C22: Session portée par un cookie inaccessible au JavaScript, application et API servies sous la même origine, plus aucun jeton conservé dans le navigateur | D22: Mr Lanto | E22: termine | F22: 1 | G22: =Parametres!$B$2+61 -> 46251 | H22: =Parametres!$B$2+61 -> 46251 | I22: 1 | J22: A01 | K22: J3 | M22: commits 7a252af (phase 0 — proxy /api, URL relative) et 7cbaf14 (phase 2 — session cookie) du 17/08 ; recette 7/7 points rejouée après le flip et parcours métier vérifié sur les 6 profils, tracée dans AUDIT.md ; proxy.conf.json et CLAUDE.md § « Backend associé — MÊME ORIGINE » | W22: ◆
A23: A19 | B23: Actualités présentées à la connexion | C23: Message d'information affiché à l'ouverture de session, écran d'administration pour le rédiger et le cibler par profil, et le service qui le délivre | D23: Mr Christian | E23: termine | F23: 1 | G23: =Parametres!$B$2+63 -> 46253 | H23: =Parametres!$B$2+63 -> 46253 | I23: 1 | J23: A08 | M23: Front : commit 9faaa14 (19/08) « modal à la connexion + administration » — shared/actualites/{actualites-modal,markdown,markdown-vue}.ts + markdown.spec.ts, services/actualite.services.ts, features/admin/actualites-admin.ts. API : commit backend 51620f4 du 19/08 également (dépôt PRS20) — ActualiteController, ActualiteDto, entités Actualite / ActualiteImage / ActualiteProfil, enum StatutActualite, tous suivis par git. CORRECTION DU 28/08 : l'activité était portée à 50 % au motif que l'API n'était pas versionnée. C'était exact au moment où docs/demande-backend-2026-08-19.md a été écrit, en cours de journée, mais le backend a commité le soir même — le document décrivait une situation en vol, pas un état final. Leçon : vérifier le dépôt concerné, pas la demande qui lui a été adressée.
A24: A20 | B24: Consultation du plan de passation en onglets | C24: Fiche de dossier réorganisée en trois onglets, avec les unités de gestion rattachées enfin visibles par les contrôleurs | D24: Mr Christian | E24: termine | F24: 1 | G24: =Parametres!$B$2+63 -> 46253 | H24: =Parametres!$B$2+64 -> 46254 | I24: 2 | J24: A09, A14 | L24: ◆ oui | M24: commits du 19/08 (« le détail du plan de passation se lit en trois onglets », f2bca57 « fin du 403 silencieux sur les UGPM ») et du 20/08 (« onglet d'identités réservé aux profils qui découvrent le dossier », « les contrôleurs voient enfin les unités de gestion rattachées ») — 3 derniers commits du dépôt
A25: A21 | B25: Tests automatisés et intégration continue | C25: Suite de tests unitaires, exécution automatique à chaque livraison, scénarios de bout en bout versionnés dans le dépôt | D25: Mr Lanto | E25: en_retard | F25: 0.33 | G25: =Parametres!$B$2+61 -> 46251 | H25: =Parametres!$B$2+63 -> 46253 | I25: 3 | J25: A01 | M25: 136 tests / 15 fichiers, 100 % au vert (`npx ng test --watch=false`, exécuté le 01/09 — était 106 / 12 au 28/08). Progression tracée dans AUDIT.md : 42 → 83 (19/08) → 93 (a11y du 27/08) → 106 (recherche serveur et pagination, 238293b) → 136 (visa unique : peutViser et la machine d'états couverts, 9e2f2cf). La CI exécute aussi ESLint 9 (.github/workflows/ci.yml). Constats « Tests » : T2 clos (CI, b350579 du 17/08), T1 toujours ENTAMÉ (couverture ni mesurée ni au niveau visé), T3 toujours OUVERT — les recettes Playwright du 01/09 (visa, intérim, chaînes de contrôle : 22/22, 31/31, 16/16) ont tourné depuis le répertoire de session, AUCUN scénario n'est versionné dans le dépôt. Avancement = 1 constat clos sur 3.
A26: A26 | B26: Polissage du module « Dossiers de planification » | C26: Reprise de finition des écrans de planification, avant que le développement ne redémarre | D26: Mr Christian | E26: termine | F26: 1 | G26: =Parametres!$B$2+68 -> 46258 | H26: =Parametres!$B$2+72 -> 46262 | I26: 5 | J26: A09, A16, A20 | L26: ◆ oui | M26: Fenêtre du 24 au 28/08 révolue à l'arrêté du 01/09, développement repris (7c89f00 le 28/08 au soir — A27). Travail versionné : sortie des sous-dialogues du détail PPM (7dfc4d8, bf991eb, 2faf937, f5cf8ec), pagination serveur de « Mes dossiers » (2f51efa), voiles de modales rendus au décor (9bcf8e3), 39 commits entre le 20 et le 28/08.
A27: A27 | B27: Visa du procès-verbal et chaînes de contrôle nominatives | C27: Avis émis par le Membre dès l'examen, clôture de la navette en un seul visa réservé au dispatcheur, suppléance par intérim justifiée par une note, et rattachements Membre → Vérificateur → Assistant ciblant la vérification et l'archivage | D27: Mr Mathieu | E27: termine | F27: 1 | G27: =Parametres!$B$2+72 -> 46262 | H27: =Parametres!$B$2+76 -> 46266 | I27: 3 | J27: A14, A16 | M27: Front : 7c89f00+0117b57 (co-signataire désigné, 28-30/08), 9e2f2cf (visa unique — avis du Membre à la soumission, visa du dispatcheur), e24c767 (visa par intérim, note PDF), 1934f6d+3eac6d8 (chaînes de contrôle : écran Admin/P/CC, files ciblées) — le backend PRS20 a livré en miroir jusqu'à f7cfe66. Recettes RÉELLES du 01/09 : PV#8 (visa normal) et PV#9 (visa par intérim) signés de bout en bout, chaînes posées à l'écran (16/16) ; e2e Playwright par interception 22/22 puis 31/31 ; en prime, cause racine CSRF (rotation du jeton × rafales) prouvée côté front et corrigée côté serveur, contre-recettée 4/4.
A28: A22 | B28: Délais réglementaires d'instruction | C28: Décompte du délai légal sur chaque dossier, alerte à l'approche de l'échéance et signalement des dépassements | D28: Mr Mathieu | E28: a_venir | F28: 0 | G28: =Parametres!$B$2+77 -> 46267 | H28: =Parametres!$B$2+90 -> 46280 | I28: 10 | J28: A02, A26, A27 | L28: ◆ oui | M28: Absent du code : 0 occurrence de `ALERTE_DELAI` dans src/ alors que docs/regles-gestion.md:370 et :485 la spécifient. Le seul dispositif temporel livré est features/prmp/calendrier-marches.ts — jalons CAPM du plan de l'autorité contractante (imminent / en retard), et non le délai d'instruction du contrôleur. Trois indicateurs déjà modélisés en dépendent : delaiMoyenExamen, delaiMoyenJours, delaiMoyCorrectionJours (models/pilotage.model.ts:85,101,116).
A29: A23 | B29: Indicateurs de performance des contrôleurs et des autorités de passation | C29: Deux écrans de restitution : activité et conformité par contrôleur, puis par autorité de passation et par exercice budgétaire | D29: Mr Christian | E29: a_venir | F29: 0 | G29: =Parametres!$B$2+77 -> 46267 | H29: =Parametres!$B$2+83 -> 46273 | I29: 5 | J29: A07, A26, A27 | M29: IndicateurCtrl et IndicateurPrmp sont modélisés (models/pilotage.model.ts:76-116) et servis (services/pilotage.services.ts) mais aucun écran ne les affiche. SNAPSHOT_STATS_CONFIG n'est plus référencé par aucune route (pilotage-resources.config.ts:6-11). Livrés par A07 : 3 écrans sur les 5 dénombrés.
A30: A24 | B30: Consultation du journal d'audit | C30: Écran de recherche du journal, filtrable par acteur, dossier, période et nature de l'action | D30: Mr Lanto | E30: termine | F30: 1 | G30: =Parametres!$B$2+71 -> 46261 | H30: =Parametres!$B$2+71 -> 46261 | I30: 1 | J30: A01 | M30: Livré le 27/08, en avance sur la date proposée (31/08) et sans attendre la fin du polissage : commit ad40144 « le journal d'audit se lit page par page, filtré par table, acteur et période ». Écran dédié features/admin/audit-logs-admin.ts, routé en admin.routes.ts:87 — il remplace le CRUD générique qui demandait la table entière (constat C-1 du nouvel audit du 27/08). État d'erreur avec reprise branché au passage (constat P9). AUDIT.md, entrée du 27/08.
A31: A25 | B31: Recette et livraison du module 1 | C31: Procès-verbal de recette signé et mise en production du module de planification | D31: Mr Lanto, Mr Mathieu, Mr Christian | E31: a_venir | F31: 0 | G31: =Parametres!$B$2+89 -> 46279 | H31: =Parametres!$B$2+93 -> 46283 | I31: 5 | J31: A17, A19, A21, A22, A23, A24 | K31: J4 | L31: ◆ oui | M31: Dates du 26/08 CONSERVÉES (14 → 18/09) mais désormais EN CONFLIT avec A22 décalée (fin 15/09) : le générateur le signale. Voir la note de A22 — l'arbitrage (compression, chevauchement ou décalage d'échéance) appartient au pilote. Dates PROPOSÉES. | AA31: ◆
A32: ▲ 01/09/2026 | X32: ▲
A34: Légende
B35: Terminé
B36: En cours
B37: À venir
B38: En retard
B39: ◆ jalon ▲ / trait orange : date d’arrêté (« aujourd’hui »)
B40: ◆ en colonne « Critique » : activité du chemin critique

Sheet Global_PRS2
A1: PRS 2.0 — Vue globale des 4 modules (Gantt mensuel)
A2: Arrêté au 01/09/2026 · 6 lignes · démarrage 17/06/2026 · échéance 18/09/2026
A3: ID | B3: Activité | C3: Livrable | D3: Responsable | E3: Statut | F3: % | G3: Début | H3: Fin | I3: Durée (j) | J3: Dépend. | K3: Jalon | L3: Critique | M3: Preuve / constat | N3: M1 | O3: M2 | P3: M3 | Q3: M4 | R3: M5 | S3: M6 | T3: M7 | U3: M8 | V3: M9 | W3: M10
A4: — | N4: =EDATE(Parametres!$B$2,0) -> 46190 | O4: =EDATE(Parametres!$B$2,1) -> 46220 | P4: =EDATE(Parametres!$B$2,2) -> 46251 | Q4: =EDATE(Parametres!$B$2,3) -> 46282 | R4: =EDATE(Parametres!$B$2,4) -> 46312 | S4: =EDATE(Parametres!$B$2,5) -> 46343 | T4: =EDATE(Parametres!$B$2,6) -> 46373 | U4: =EDATE(Parametres!$B$2,7) -> 46404 | V4: =EDATE(Parametres!$B$2,8) -> 46435 | W4: =EDATE(Parametres!$B$2,9) -> 46463
A5: G01 | B5: Module 1 — Socle transversal et dossiers de planification | C5: Authentification, habilitations, référentiels, circuit d'instruction, délais réglementaires, notifications, journal d'audit et tableaux de bord — appliqués au contrôle des plans de passation | D5: Mr Lanto, Mr Mathieu, Mr Christian | E5: en_cours | F5: 0.89 | G5: =Parametres!$B$2+0 -> 46190 | H5: =Parametres!$B$2+93 -> 46283 | I5: 67 | K5: J4 | L5: ◆ oui | M5: Inventaire des 14 fonctions du module 1, réexaminé le 28/08 : 12 implémentées (authentification, habilitations, référentiels, dépôt, complétude, affectation, instruction, visa, navette, notifications, journal d'audit, actualités), 1 partielle (statistiques — les écrans d'indicateurs par contrôleur et par autorité de passation manquent, cf. A23), 1 absente (délais réglementaires, cf. A22). Avancement = (12×100 + 1×50 + 1×0) / 14 = 89 %. Deux fonctions ont changé de statut depuis le 26/08 : le journal d'audit passe de partielle à implémentée (écran dédié livré le 27/08, A24) et les actualités de partielle à implémentée (l'API backend était en réalité commitée dès le 19/08, A19). Réexaminé le 01/09 : INCHANGÉ à 89 % — le chantier A27 (visa, intérim, chaînes de contrôle) approfondit des fonctions déjà comptées implémentées (visa, navette, habilitations) sans faire bouger les deux manquantes (délais, statistiques). Le détail fonction par fonction est porté par les activités A01 à A27 de ce fichier, chacune avec sa propre preuve — commit, fichier du dépôt (src/app/…) ou exécution de test. | Q5: ◆
A6: G02 | B6: Recette et mise en production du module 1 | C6: Procès-verbal de recette, déploiement en production et reprise des réserves | D6: Mr Lanto, Mr Mathieu, Mr Christian | E6: a_venir | F6: 0 | G6: =Parametres!$B$2+96 -> 46286 | H6: =Parametres!$B$2+121 -> 46311 | I6: 20 | J6: G01 | M6: Découpage PROPOSÉ — aucun calendrier contractuel au-delà des 3 mois n'est connu.
A7: G03 | B7: Module 2 — Dossiers de mise en concurrence | C7: Contrôle des dossiers d'appel à concurrence, des procédures dérogatoires et des rapports d'évaluation | D7: Mr Lanto, Mr Mathieu, Mr Christian | E7: a_venir | F7: 0 | G7: =Parametres!$B$2+96 -> 46286 | H7: =Parametres!$B$2+156 -> 46346 | I7: 45 | J7: G01 | K7: J5 | L7: ◆ oui | M7: Amorce constatée dans le dépôt : le dépôt d'un dossier DMC et son passage dans le circuit générique existent (soumettre-dossier.ts:57-61 et :158, models/prmp.model.ts:312 « saisie sans contenu »), mais aucun contenu métier propre au module (rapport d'évaluation, procédure dérogatoire) n'est implémenté. | S7: ◆
A8: G04 | B8: Module 3 — Dossiers de marchés | C8: Contrôle des projets de marchés et des avenants avant approbation | D8: Mr Lanto, Mr Mathieu, Mr Christian | E8: a_venir | F8: 0 | G8: =Parametres!$B$2+159 -> 46349 | H8: =Parametres!$B$2+219 -> 46409 | I8: 45 | J8: G03 | K8: J6 | L8: ◆ oui | M8: Amorce identique à DMC (famille DDM, soumettre-dossier.ts:166) ; aucun projet de marché ni avenant structuré dans le code. | U8: ◆
A9: G05 | B9: Module 4 — Actes de gestion contractuelle | C9: Contrôle des décisions d'octroi d'indemnité, de sursis d'exécution, de remise de pénalité et de résiliation | D9: Mr Lanto, Mr Mathieu, Mr Christian | E9: a_venir | F9: 0 | G9: =Parametres!$B$2+222 -> 46412 | H9: =Parametres!$B$2+268 -> 46458 | I9: 35 | J9: G04 | K9: J7 | L9: ◆ oui | M9: Absent du dépôt : 0 occurrence de « indemnité », « sursis », « pénalité » ou « résiliation » dans src/. | V9: ◆
A10: G06 | B10: Recette générale et mise en production de PRS 2.0 | C10: Recette des quatre modules, reprise des données et déploiement en production | D10: Mr Lanto, Mr Mathieu, Mr Christian | E10: a_venir | F10: 0 | G10: =Parametres!$B$2+271 -> 46461 | H10: =Parametres!$B$2+303 -> 46493 | I10: 25 | J10: G02, G03, G04, G05 | K10: J8 | L10: ◆ oui | M10: Un mois, durée inchangée : le pilote n'a arbitré que les modules 2, 3 et 4 le 26/08. À revoir si la compression des trois modules reporte de la charge sur la recette globale. | W10: ◆
A11: ▲ 01/09/2026 | P11: ▲
A13: Légende
B14: Terminé
B15: En cours
B16: À venir
B17: En retard
B18: ◆ jalon ▲ / trait orange : date d’arrêté (« aujourd’hui »)
B19: ◆ en colonne « Critique » : activité du chemin critique

Sheet Jalons
A1: PRS 2.0 — Jalons
A3: Code | B3: Libellé | C3: Date cible | D3: Statut | E3: Critères de validation | F3: Preuve
A4: ◆ J1 | B4: Circuit d'instruction fonctionnel de bout en bout | C4: =Parametres!$B$2+8 -> 46198 | D4: franchi | E4: • Un dossier parcourt dépôt → réception → dispatch → examen → PV sans intervention manuelle • Les deux issues de l'examen sont ouvertes : projet de PV ou lettre de renvoi • Les 6 profils du circuit disposent de leurs écrans | F4: Écrans du circuit et de la lettre de renvoi créés entre le 17/06 et le 25/06 ; circuit-workflow.spec.ts au vert
A5: ◆ J2 | B5: Parcours métier complet sur les 6 profils | C5: =Parametres!$B$2+40 -> 46230 | D5: franchi | E5: • Chaque profil atterrit sur sa file de travail à la connexion • Les familles DDP / DMC / DDM et les sous-types sont pilotés par référentiel • L'entité contractante est résolue ou créée au dépôt, avec approbation Admin • Les écrans redondants sont supprimés au profit de « Mes dossiers » | F5: Commits du 26 et 27/07 (40 au total) ; features/circuit/dossiers-classement.ts, features/president/dispatchs-controleurs.ts
A6: ◆ J3 | B6: Socle durci : sécurité, accessibilité, session par cookie | C6: =Parametres!$B$2+63 -> 46253 | D6: partiellement_franchi | E6: • Volet sécurité de l'audit intégralement soldé — ✅ (AUDIT.md : S10 clos le 17/08) • Aucun jeton côté client, session portée par cookie HttpOnly — ✅ (recette 7/7, 6 profils) • npm audit sans vulnérabilité ≥ high, bloquant en CI — ✅ (ci.yml) • Contraste AA sur le texte de l'application — ✅ partiel (114 textes hors seuil → 17) • 8 constats d'audit restent ouverts : P1, P9, A2b, S9, S12, P10, T1, T3 — ❌ | F6: AUDIT.md, suivi des corrections du 16 au 19/08 ; commits 787ec4a → 1c4ab1c
A7: ◆ J4 | B7: Recette du module 1 — livraison contractuelle | C7: =Parametres!$B$2+93 -> 46283 | D7: a_venir | E7: • Les 14 fonctions du module 1 sont implémentées, dont les délais légaux d'instruction • Les 35 constats de l'audit technique sont soldés ou explicitement acceptés • Scénarios e2e versionnés dans le dépôt (constat T3) • API des actualités commitée et déployable depuis git • PV de recette signé
A8: ◆ J5 | B8: Module 2 — Dossiers de mise en concurrence livré | C8: =Parametres!$B$2+156 -> 46346 | D8: a_venir | E8: • À définir avec la maîtrise d'ouvrage — aucune spécification dans le dépôt
A9: ◆ J6 | B9: Module 3 — Dossiers de marchés livré | C9: =Parametres!$B$2+219 -> 46409 | D9: a_venir | E9: • À définir avec la maîtrise d'ouvrage — aucune spécification dans le dépôt
A10: ◆ J7 | B10: Module 4 — Actes livré | C10: =Parametres!$B$2+268 -> 46458 | D10: a_venir | E10: • À définir avec la maîtrise d'ouvrage — aucune spécification dans le dépôt
A11: ◆ J8 | B11: Mise en production PRS 2.0 | C11: =Parametres!$B$2+303 -> 46493 | D11: a_venir | E11: • À définir avec la maîtrise d'ouvrage

Sheet Parametres
A1: Paramètre | B1: Valeur | C1: Commentaire
A2: Date de démarrage | B2: 46190 | C2: ANCRE du classeur : toutes les dates des autres onglets sont des formules « =Parametres!$B$2 + n ». Modifier cette cellule décale le calendrier ; relancer le script pour recalculer les couleurs des barres.
A3: Date d'arrêté | B3: 46266 | C3: Date d'observation — sert à la détection des retards et à la ligne « aujourd'hui ».
A4: Date de fin contractuelle | B4: 46283 | C4: Échéance. Écart au démarrage : 93 jours calendaires.
A5: Jours ouvrés | B5: oui | C5: Week-ends exclus du calcul des durées.
A6: Jours fériés exclus | B6: 2026-06-26, 2026-08-15 | C6: Renseignés dans activites.yaml → parametres.jours_feries.
A7: Équipe | B7: Mr Lanto, Mr Mathieu, Mr Christian
A9: SYNTHÈSE
A10: Activités module 1 | B10: 27 | C10: 22 terminées · 0 en cours · 3 à venir
A11: Avancement pondéré (durées) | B11: 83 % | C11: Σ(avancement × durée) / Σ(durée) sur le module 1.
A12: Avancement module 1 déclaré | B12: 89 % | C12: Valeur portée par la ligne globale, adossée à sa preuve.
A13: Activités en retard | B13: 2 | C13: A17, A21
A14: Jalons franchis | B14: 3 | C14: J1, J2, J3
A15: Prochaine échéance | B15: 18/09/2026 | C15: J4 — Recette du module 1 — livraison contractuelle (dans 17 jours)
A16: Chemin critique — module 1 | B16: A01 → A02 → A09 → A10 → A12 → A14 → A20 → A26 → A22 → A25 | C16: 10 activités.
A17: Chemin critique — global | B17: G01 → G03 → G04 → G05 → G06 | C17: 5 lignes.
A20: AVERTISSEMENTS (15)
A21: • A06 : début déclaré le 26/06/2026 (jour non ouvré) → décalé au 29/06/2026.
A22: • A02 : démarre le 17/06/2026, avant la fin de sa dépendance A01 (19/06/2026) — chevauchement assumé, non replanifié.
A23: • A03 : démarre le 18/06/2026, avant la fin de sa dépendance A02 (25/06/2026) — chevauchement assumé, non replanifié.
A24: • A04 : démarre le 19/06/2026, avant la fin de sa dépendance A02 (25/06/2026) — chevauchement assumé, non replanifié.
A25: • A05 : démarre le 24/06/2026, avant la fin de sa dépendance A02 (25/06/2026) — chevauchement assumé, non replanifié.
A26: • A07 : démarre le 29/06/2026, avant la fin de sa dépendance A06 (30/06/2026) — chevauchement assumé, non replanifié.
A27: • A09 : démarre le 23/06/2026, avant la fin de sa dépendance A02 (25/06/2026) — chevauchement assumé, non replanifié.
A28: • A10 : démarre le 16/07/2026, avant la fin de sa dépendance A08 (16/07/2026) — chevauchement assumé, non replanifié.
A29: • A10 : démarre le 16/07/2026, avant la fin de sa dépendance A09 (27/07/2026) — chevauchement assumé, non replanifié.
A30: • A11 : démarre le 27/07/2026, avant la fin de sa dépendance A09 (27/07/2026) — chevauchement assumé, non replanifié.
A31: • A12 : démarre le 27/07/2026, avant la fin de sa dépendance A10 (27/07/2026) — chevauchement assumé, non replanifié.
... A35: • A25 : démarre le 14/09/2026, avant la fin de sa dépendance A22 (15/09/2026) — chevauchement assumé, non replanifié.
